AUTHORS
CHANGELOG
INSTALL
LICENSE
MANIFEST.in
README
README.rst
THANKS
TODO
setup.py
doc/3rd-party-apps.rst
doc/Makefile
doc/admin-screenshot1.png
doc/changelog.rst
doc/commands.rst
doc/conf.py
doc/display-content.rst
doc/index.rst
doc/installation.rst
doc/introduction.rst
doc/navigation-template-tags.rst
doc/page-api.rst
doc/placeholders.rst
doc/settings-list.rst
doc/nature/layout.html
doc/nature/theme.conf
doc/nature/static/gerbi.png
doc/nature/static/gerbi.xcf
doc/nature/static/nature.css_t
doc/nature/static/pygments.css
pages/__init__.py
pages/context_processors.py
pages/http.py
pages/managers.py
pages/models.py
pages/permissions.py
pages/placeholders.py
pages/search_indexes.py
pages/settings.py
pages/test_runner.py
pages/urlconf_registry.py
pages/urls.py
pages/utils.py
pages/views.py
pages/widgets.py
pages/widgets_registry.py
pages/admin/__init__.py
pages/admin/actions.py
pages/admin/forms.py
pages/admin/utils.py
pages/admin/views.py
pages/fixtures/pages_tests.json
pages/locale/da/LC_MESSAGES/django.mo
pages/locale/da/LC_MESSAGES/django.po
pages/locale/de/LC_MESSAGES/django.mo
pages/locale/de/LC_MESSAGES/django.po
pages/locale/de/LC_MESSAGES/djangojs.mo
pages/locale/de/LC_MESSAGES/djangojs.po
pages/locale/es/LC_MESSAGES/django.mo
pages/locale/es/LC_MESSAGES/django.po
pages/locale/fr/LC_MESSAGES/django.mo
pages/locale/fr/LC_MESSAGES/django.po
pages/locale/he/LC_MESSAGES/django.mo
pages/locale/he/LC_MESSAGES/django.po
pages/locale/it/LC_MESSAGES/django.mo
pages/locale/it/LC_MESSAGES/django.po
pages/locale/nl/LC_MESSAGES/django.mo
pages/locale/nl/LC_MESSAGES/django.po
pages/locale/ru/LC_MESSAGES/django.mo
pages/locale/ru/LC_MESSAGES/django.po
pages/locale/ru/LC_MESSAGES/djangojs.mo
pages/locale/ru/LC_MESSAGES/djangojs.po
pages/locale/sk/LC_MESSAGES/django.mo
pages/locale/sk/LC_MESSAGES/django.po
pages/management/__init__.py
pages/management/commands/__init__.py
pages/management/commands/pages_export_po.py
pages/management/commands/pages_import_po.py
redsolutioncms.django_page_cms.egg-info/PKG-INFO
redsolutioncms.django_page_cms.egg-info/SOURCES.txt
redsolutioncms.django_page_cms.egg-info/dependency_links.txt
redsolutioncms.django_page_cms.egg-info/not-zip-safe
redsolutioncms.django_page_cms.egg-info/requires.txt
redsolutioncms.django_page_cms.egg-info/top_level.txt
