Metadata-Version: 1.0
Name: redsolutioncms.django-page-cms
Version: 1.4.5
Summary: A tree based Django CMS application
Home-page: http://packages.python.org/django-page-cms/
Author: Batiste Bieler
Author-email: batiste.bieler@gmail.com
License: BSD
Download-URL: http://pypi.python.org/packages/source/d/redsolutioncms.django-page-cms/redsolutioncms.django-page-cms-1.4.5.tar.gz
Platform: UNKNOWN
Classifier: Development Status :: 5 - Production/Stable
Classifier: Environment :: Web Environment
Classifier: Intended Audience :: Developers
Classifier: License :: OSI Approved :: BSD License
Classifier: Operating System :: OS Independent
Classifier: Programming Language :: Python
Classifier: Framework :: Django
Classifier: Programming Language :: Python :: 2.3
Classifier: Programming Language :: JavaScript
Classifier: Topic :: Internet :: WWW/HTTP :: Site Management
